aiida_upgrade/__init__.py
aiida_upgrade/__main__.py
aiida_upgrade/entry_points.py
aiida_upgrade/methods.py
aiida_upgrade/migrate.py
aiida_upgrade-0.1.0.dist-info/entry_points.txt
aiida_upgrade-0.1.0.dist-info/LICENSE
aiida_upgrade-0.1.0.dist-info/WHEEL
aiida_upgrade-0.1.0.dist-info/METADATA
aiida_upgrade-0.1.0.dist-info/RECORD
