Metadata-Version: 2.1
Name: aiida_upgrade
Version: 0.1.0
Summary: A tool to perform upgrades of AiiDA plugins to new aiida-core versions.
Author-email: The AiiDA team <developers@aiida.net>
Classifier: License :: OSI Approved :: MIT License
Requires-Dist: click
Requires-Dist: libcst
Requires-Dist: pytest ; extra == "tests"
Project-URL: Home, https://github.com/aiidateam/aiida-upgrade
Provides-Extra: tests
